{
    "keep": {
        "days": true,
        "amount": 14
    },
    "auditLog": "D:\\WebDev_Level-2\\Assignments\\Assignment-9\\ll-backend\\logs\\winston\\errors\\.0c31a7986317412dcecdd852f1a12fb41216cf79-audit.json",
    "files": [
        {
            "date": 1697088719396,
            "name": "D:\\WebDev_Level-2\\Assignments\\Assignment-9\\ll-backend\\logs\\winston\\errors\\phu-2023-12-10-11-error.log",
            "hash": "0f17a3ad5bf05434bcc431dd461147bd013faec9ab74d6363767c847e3eec1ef"
        },
        {
            "date": 1697090683525,
            "name": "D:\\WebDev_Level-2\\Assignments\\Assignment-9\\ll-backend\\logs\\winston\\errors\\phu-2023-12-10-12-error.log",
            "hash": "c1e51e9d7627dd1a89e2a9fa24dc51293efeefc32c0b7ec1c925fb5e794f5812"
        },
        {
            "date": 1697108547764,
            "name": "D:\\WebDev_Level-2\\Assignments\\Assignment-9\\ll-backend\\logs\\winston\\errors\\phu-2023-12-10-17-error.log",
            "hash": "9b847d16cbd248b0cff82517cd26368e1712049d91e1a734f74bd10a09094f3c"
        },
        {
            "date": 1697113078586,
            "name": "D:\\WebDev_Level-2\\Assignments\\Assignment-9\\ll-backend\\logs\\winston\\errors\\phu-2023-12-10-18-error.log",
            "hash": "c781485c39a214653d65057dc15c95071ac9d0e98856bc35283a1115f7bfd6b8"
        },
        {
            "date": 1697185741294,
            "name": "D:\\WebDev_Level-2\\Assignments\\Assignment-9\\ll-backend\\logs\\winston\\errors\\phu-2023-13-10-14-error.log",
            "hash": "747ea29a6dde726eda7b554d5c1d00a1f49fc89e9f8047f96d1bb5f5f0335a4f"
        },
        {
            "date": 1697190072970,
            "name": "D:\\WebDev_Level-2\\Assignments\\Assignment-9\\ll-backend\\logs\\winston\\errors\\phu-2023-13-10-15-error.log",
            "hash": "e11c111c343896ce6ca0e90a8a2eb8a2e6840788ba7614e0e874bddff88bd868"
        },
        {
            "date": 1697191770480,
            "name": "D:\\WebDev_Level-2\\Assignments\\Assignment-9\\ll-backend\\logs\\winston\\errors\\phu-2023-13-10-16-error.log",
            "hash": "2bac3f22e233c50699acd54f511ae6e0131c62136ecdac362ad67c89bc572ad8"
        },
        {
            "date": 1697204300605,
            "name": "D:\\WebDev_Level-2\\Assignments\\Assignment-9\\ll-backend\\logs\\winston\\errors\\phu-2023-13-10-19-error.log",
            "hash": "37e37562b8dee7be8b32d0493707bf0c3b55ebbfe56d57cc12df8c241697b89e"
        },
        {
            "date": 1697210635328,
            "name": "D:\\WebDev_Level-2\\Assignments\\Assignment-9\\ll-backend\\logs\\winston\\errors\\phu-2023-13-10-21-error.log",
            "hash": "dec2f6690dc3e0d64d069f7c3bc8b3cfa6691d3ecc0644214052bbe6be4dd61c"
        },
        {
            "date": 1697486715321,
            "name": "D:\\WebDev_Level-2\\Assignments\\Assignment-9\\ll-backend\\logs\\winston\\errors\\phu-2023-17-10-02-error.log",
            "hash": "4662de872277e1ef9c0347333ff8da2d898195024eb7eedf3000da4c86b7dace"
        },
        {
            "date": 1697490121946,
            "name": "D:\\WebDev_Level-2\\Assignments\\Assignment-9\\ll-backend\\logs\\winston\\errors\\phu-2023-17-10-03-error.log",
            "hash": "763dd569c1c0a67107177d9746b84f638ad0ee176dc30d34136fe003c3d74c58"
        },
        {
            "date": 1697510924064,
            "name": "D:\\WebDev_Level-2\\Assignments\\Assignment-9\\ll-backend\\logs\\winston\\errors\\phu-2023-17-10-08-error.log",
            "hash": "4f280c1e09acb98b34c820f4a3525e921a90ec9d7fb1459283994a5e426820cc"
        },
        {
            "date": 1697511989307,
            "name": "D:\\WebDev_Level-2\\Assignments\\Assignment-9\\ll-backend\\logs\\winston\\errors\\phu-2023-17-10-09-error.log",
            "hash": "edfbbd83071b530c642f444d7018e487c0fde46b04392937c417823d5d38dfb0"
        },
        {
            "date": 1697535387097,
            "name": "D:\\WebDev_Level-2\\Assignments\\Assignment-9\\ll-backend\\logs\\winston\\errors\\phu-2023-17-10-15-error.log",
            "hash": "197619e3ca95144463affad022034d89020417edd8731d3fc383507ae0d6863b"
        },
        {
            "date": 1697541137124,
            "name": "D:\\WebDev_Level-2\\Assignments\\Assignment-9\\ll-backend\\logs\\winston\\errors\\phu-2023-17-10-17-error.log",
            "hash": "873f2a1a5b03f6bab0519295ed7b678b3872cd3067fac8c3165c45b81ffb291a"
        },
        {
            "date": 1697547287575,
            "name": "D:\\WebDev_Level-2\\Assignments\\Assignment-9\\ll-backend\\logs\\winston\\errors\\phu-2023-17-10-18-error.log",
            "hash": "4395226186f3567daf3912f44f05e9a94ef7e575761856e072fb93d810ebed2c"
        },
        {
            "date": 1697548298950,
            "name": "D:\\WebDev_Level-2\\Assignments\\Assignment-9\\ll-backend\\logs\\winston\\errors\\phu-2023-17-10-19-error.log",
            "hash": "a36bd45fd700a72a796c51f80f3198d91c599110a0d33a131bd210b31979a3b4"
        }
    ],
    "hashType": "sha256"
}